examples/basic_usage.py
examples/data/daugaard_matlab.xlsx
examples/data/daugaard_standard.xlsx
examples/data/daugaard_valley.xlsx
geoprior1d/__init__.py
geoprior1d/cli.py
geoprior1d/colormaps.py
geoprior1d/core.py
geoprior1d/io.py
geoprior1d/lithology.py
geoprior1d/resistivity.py
geoprior1d/sampling.py
geoprior1d/visualization.py
geoprior1d/water.py
geoprior1d-0.9.9.1.dist-info/licenses/LICENSE
geoprior1d-0.9.9.1.dist-info/METADATA
geoprior1d-0.9.9.1.dist-info/WHEEL
geoprior1d-0.9.9.1.dist-info/entry_points.txt
geoprior1d-0.9.9.1.dist-info/top_level.txt
geoprior1d-0.9.9.1.dist-info/RECORD
