Metadata-Version: 2.4
Name: geoprior1d
Version: 0.9.9.1
Summary: 1D geological prior generator for stochastic lithology and resistivity modeling
Author-email: Jesper Nørgaard <jesn@geus.dk>
Maintainer-email: Thomas Mejer Hansen <cultpenguin@gmail.com>
License: MIT
Project-URL: Homepage, https://github.com/GEUSjesper/geoprior1d
Project-URL: Documentation, https://github.com/GEUSjesper/geoprior1d/blob/main/README.md
Project-URL: Repository, https://github.com/GEUSjesper/geoprior1d
Project-URL: Issues, https://github.com/GEUSjesper/geoprior1d/issues
Keywords: geophysics,geology,resistivity,lithology,prior,stochastic,monte-carlo,subsurface
Classifier: Development Status :: 4 - Beta
Classifier: Intended Audience :: Science/Research
Classifier: Topic :: Scientific/Engineering
Classifier: License :: OSI Approved :: MIT License
Classifier: Programming Language :: Python :: 3
Classifier: Programming Language :: Python :: 3.8
Classifier: Programming Language :: Python :: 3.9
Classifier: Programming Language :: Python :: 3.10
Classifier: Programming Language :: Python :: 3.11
Classifier: Programming Language :: Python :: 3.12
Requires-Python: >=3.8
License-File: LICENSE
Requires-Dist: numpy>=1.20.0
Requires-Dist: h5py>=3.0.0
Requires-Dist: matplotlib>=3.3.0
Requires-Dist: pandas>=1.2.0
Requires-Dist: scipy>=1.6.0
Requires-Dist: tqdm>=4.60.0
Requires-Dist: openpyxl>=3.0.0
Dynamic: license-file
